vidgear/__init__.py
vidgear/version.py
vidgear/gears/__init__.py
vidgear/gears/camgear.py
vidgear/gears/helper.py
vidgear/gears/netgear.py
vidgear/gears/pigear.py
vidgear/gears/screengear.py
vidgear/gears/stabilizer.py
vidgear/gears/streamgear.py
vidgear/gears/videogear.py
vidgear/gears/writegear.py
vidgear/gears/asyncio/__init__.py
vidgear/gears/asyncio/__main__.py
vidgear/gears/asyncio/helper.py
vidgear/gears/asyncio/netgear_async.py
vidgear/gears/asyncio/webgear.py
vidgear/gears/asyncio/webgear_rtc.py
vidgear-0.3.4.dist-info/licenses/LICENSE
vidgear-0.3.4.dist-info/METADATA
vidgear-0.3.4.dist-info/WHEEL
vidgear-0.3.4.dist-info/top_level.txt
vidgear-0.3.4.dist-info/RECORD
