Metadata-Version: 2.4
Name: vidgear
Version: 0.3.4
Summary: High-performance cross-platform Video Processing Python framework powerpacked with unique trailblazing features.
Home-page: https://abhitronix.github.io/vidgear
Author: Abhishek Thakur
Author-email: abhi.una12@gmail.com
License: Apache License 2.0
Project-URL: Bug Reports, https://github.com/abhiTronix/vidgear/issues
Project-URL: Funding, https://ko-fi.com/W7W8WTYO
Project-URL: Source, https://github.com/abhiTronix/vidgear
Project-URL: Documentation, https://abhitronix.github.io/vidgear
Project-URL: Changelog, https://abhitronix.github.io/vidgear/latest/changelog/
Keywords: OpenCV,multithreading,FFmpeg,picamera,starlette,mss,pyzmq,dxcam,aiortc,uvicorn,uvloop,yt-dlp,asyncio,dash,hls,Video Processing,Video Stabilization,Computer Vision,Video Streaming,raspberrypi,YouTube,Twitch,WebRTC
Classifier: Development Status :: 5 - Production/Stable
Classifier: Operating System :: POSIX
Classifier: Operating System :: MacOS :: MacOS X
Classifier: Operating System :: Microsoft :: Windows
Classifier: Topic :: Multimedia :: Video
Classifier: Topic :: Scientific/Engineering
Classifier: Intended Audience :: Developers
Classifier: Intended Audience :: Science/Research
Classifier: Intended Audience :: Education
Classifier: License :: OSI Approved :: Apache Software License
Classifier: Programming Language :: Python :: 3.10
Classifier: Programming Language :: Python :: 3.11
Classifier: Programming Language :: Python :: 3.12
Classifier: Programming Language :: Python :: 3.13
Requires-Python: >=3.10
License-File: LICENSE
Requires-Dist: cython
Requires-Dist: numpy
Requires-Dist: requests
Requires-Dist: colorlog
Requires-Dist: tqdm
Requires-Dist: packaging
Provides-Extra: core
Requires-Dist: yt-dlp[default]>=2025.11.12.5349.dev0; extra == "core"
Requires-Dist: pyzmq>=27.1.0; extra == "core"
Requires-Dist: Pillow; extra == "core"
Requires-Dist: simplejpeg>=1.9.0; extra == "core"
Requires-Dist: mss>=10.1.0; extra == "core"
Requires-Dist: pyscreenshot>=3.1; extra == "core"
Provides-Extra: asyncio
Requires-Dist: yt-dlp[default]>=2025.11.12.5349.dev0; extra == "asyncio"
Requires-Dist: pyzmq>=27.1.0; extra == "asyncio"
Requires-Dist: simplejpeg>=1.9.0; extra == "asyncio"
Requires-Dist: mss>=10.1.0; extra == "asyncio"
Requires-Dist: Pillow; extra == "asyncio"
Requires-Dist: pyscreenshot>=3.1; extra == "asyncio"
Requires-Dist: starlette>=0.50.0; extra == "asyncio"
Requires-Dist: jinja2; extra == "asyncio"
Requires-Dist: msgpack>=1.1.2; extra == "asyncio"
Requires-Dist: msgpack_numpy>=0.4.8; extra == "asyncio"
Requires-Dist: aiortc>=1.14.0; extra == "asyncio"
Requires-Dist: uvicorn>=0.38.0; extra == "asyncio"
Dynamic: author
Dynamic: author-email
Dynamic: classifier
Dynamic: description
Dynamic: description-content-type
Dynamic: home-page
Dynamic: keywords
Dynamic: license
Dynamic: license-file
Dynamic: project-url
Dynamic: provides-extra
Dynamic: requires-dist
Dynamic: requires-python
Dynamic: summary
